datasets/__init__.py
datasets/pl_data.py
datasets/pl_pair_dataset.py
scripts/__init__.py
scripts/cross_dock.py
scripts/dock_extended_baseline.py
scripts/evaluate_diffusion.py
scripts/evalueate_valnet.py
scripts/sample_diffusion.py
scripts/sample_for_pocket.py
scripts/train_diffusion.py
scripts/data_preparation/__init__.py
scripts/data_preparation/clean_crossdocked.py
scripts/data_preparation/extend_protein_extract.py
scripts/data_preparation/extract_pockets.py
scripts/data_preparation/inject_affinity.py
scripts/data_preparation/split_pl_dataset.py
KGDiff-0.1.2.dist-info/LICENSE
KGDiff-0.1.2.dist-info/METADATA
KGDiff-0.1.2.dist-info/WHEEL
KGDiff-0.1.2.dist-info/entry_points.txt
KGDiff-0.1.2.dist-info/top_level.txt
KGDiff-0.1.2.dist-info/RECORD
